instaui_echarts/__init__.py
instaui_echarts/_echarts.py
instaui_echarts/consts.py
instaui_echarts/mixins.py
instaui_echarts/types.py
instaui_echarts/version.py
instaui_echarts/cdn/__init__.py
instaui_echarts/cdn/_cdn.py
instaui_echarts/graphics/__init__.py
instaui_echarts/graphics/_axis.py
instaui_echarts/graphics/_data.py
instaui_echarts/graphics/_facet.py
instaui_echarts/graphics/_marks.py
instaui_echarts/graphics/_options.py
instaui_echarts/graphics/_protocols.py
instaui_echarts/graphics/_tooltip.py
instaui_echarts/graphics/_types.py
instaui_echarts/systems/dict_systems.py
instaui_echarts/static/echarts.esm.min.js
instaui_echarts/static/instaui-echarts.js
instaui_echarts-0.5.0.dist-info/METADATA
instaui_echarts-0.5.0.dist-info/WHEEL
instaui_echarts-0.5.0.dist-info/licenses/LICENSE
instaui_echarts-0.5.0.dist-info/RECORD
