Metadata-Version: 2.4
Name: instaui-echarts
Version: 0.5.0
Summary: A Python package for instaui-echarts.
Author-email: CrystalWindSnake <568166495@qq.com>
License-Expression: MIT
License-File: LICENSE
Keywords: charts,data-visualization,echarts,gui,instaui,ui,web
Requires-Python: <3.14,>=3.10
Requires-Dist: instaui>=0.8.1
